InputPowertools/__init__.py
InputPowertools/cli.py
InputPowertools/input.py
inputpowertools-1.0.4.dist-info/METADATA
inputpowertools-1.0.4.dist-info/WHEEL
inputpowertools-1.0.4.dist-info/RECORD
