Metadata-Version: 2.3
Name: InputPowertools
Version: 1.0.4
Summary: Kind of like a non intrusive addon for the standard input()
Project-URL: Homepage, https://github.com/MAA28/InputPowertools
Project-URL: Issues, https://github.com/MAA28/InputPowertools/issues
Author: MAA28
Keywords: cli,command line
Classifier: Development Status :: 5 - Production/Stable
Classifier: Environment :: Console
Classifier: Intended Audience :: Developers
Classifier: Intended Audience :: System Administrators
Classifier: License :: OSI Approved :: MIT License
Classifier: Programming Language :: Python :: 3 :: Only
Classifier: Topic :: Software Development :: User Interfaces
Requires-Python: >=3.0
Requires-Dist: colorama
Requires-Dist: docstring-parser==0.16
Requires-Dist: typical
Requires-Dist: typing
